LICENSE
MANIFEST.in
README.md
requirements.txt
setup.py
vaby/__init__.py
vaby/_version.py
vaby/cli.py
vaby/data.py
vaby/dist.py
vaby/inference.py
vaby/main.py
vaby/model.py
vaby/parameter.py
vaby/utils.py
vaby.egg-info/PKG-INFO
vaby.egg-info/SOURCES.txt
vaby.egg-info/dependency_links.txt
vaby.egg-info/entry_points.txt
vaby.egg-info/requires.txt
vaby.egg-info/top_level.txt
vaby/models/__init__.py
vaby/models/exp.py
vaby/models/misc.py
vaby/structures/__init__.py
vaby/structures/base.py
vaby/structures/model.py
vaby/structures/surface.py
vaby/structures/volume.py
vaby/test/__init__.py
vaby/test/test_composite_structure.py
vaby/test/test_cortical_surface.py
vaby/test/test_volume.py