Metadata-Version: 2.1
Name: vaby
Version: 0.2.0.post1
Summary: Core code for implementation of Variational Bayes for timeseries model fitting
Author: Martin Craig
Author-email: martin.craig@eng.ox.ac.uk
License: Apache 2
Classifier: Intended Audience :: Science/Research
Classifier: Programming Language :: Python :: 3
Classifier: Topic :: Scientific/Engineering :: Bio-Informatics
Classifier: License :: OSI Approved :: Apache Software License
License-File: LICENSE
